komodo_api/__init__.py
komodo_api/exceptions.py
komodo_api/lib.py
komodo_api/responses.py
komodo_api/types.py
komodo_api-1.19.4.dist-info/METADATA
komodo_api-1.19.4.dist-info/WHEEL
komodo_api-1.19.4.dist-info/licenses/LICENSE
komodo_api-1.19.4.dist-info/RECORD
