Metadata-Version: 2.4
Name: komodo-api
Version: 1.19.4
Summary: Komodo client API
Project-URL: Homepage, https://github.com/dkarv/komodo-api
Project-URL: Issues, https://github.com/dkarv/komodo-api/issues
Author-email: David Punzet <punzet.david@gmail.com>
License-Expression: GPL-3.0-only
License-File: LICENSE
Classifier: Operating System :: OS Independent
Classifier: Programming Language :: Python :: 3
Requires-Python: >=3.9
Requires-Dist: aiohttp
Requires-Dist: pydantic
